setup.py
cratis_i18n/__init__.py
cratis_i18n/context.py
cratis_i18n/features.py
cratis_i18n/middleware.py
cratis_i18n/translate.py
cratis_i18n/utils.py
cratis_i18n/templatetags/__init__.py
cratis_i18n/templatetags/model_trans.py
django_cratis_i18n.egg-info/PKG-INFO
django_cratis_i18n.egg-info/SOURCES.txt
django_cratis_i18n.egg-info/dependency_links.txt
django_cratis_i18n.egg-info/requires.txt
django_cratis_i18n.egg-info/top_level.txt