Metadata-Version: 1.0
Name: django-cratis-i18n
Version: 0.1.2
Summary: I18n support
Home-page: UNKNOWN
Author: Alex Rudakov
Author-email: ribozz@gmail.com
License: MIT
Platform: UNKNOWN
